obfusc8/__init__.py
obfusc8/obfuscate.py
obfusc8-0.1.1.dist-info/LICENSE
obfusc8-0.1.1.dist-info/METADATA
obfusc8-0.1.1.dist-info/WHEEL
obfusc8-0.1.1.dist-info/top_level.txt
obfusc8-0.1.1.dist-info/RECORD
