Metadata-Version: 2.1
Name: obfusc8
Version: 0.1.1
Summary: Tools for code obfuscation in python
Author: adesanjo
License: MIT License        
Project-URL: Homepage, https://github.com/adesanjo/obfusc8
Keywords: obfuscate,obfuscation,obfuscated,obfusc8
Classifier: License :: OSI Approved :: MIT License
Classifier: Programming Language :: Python
Classifier: Programming Language :: Python :: 3
Requires-Python: >=3.10
License-File: LICENSE
Provides-Extra: dev
